setup.py
loggly/__init__.py
loggly/handlers.py
loggly_handler.egg-info/PKG-INFO
loggly_handler.egg-info/SOURCES.txt
loggly_handler.egg-info/dependency_links.txt
loggly_handler.egg-info/requires.txt
loggly_handler.egg-info/top_level.txt