Metadata-Version: 1.1
Name: loggly-handler
Version: 0.1.1
Summary: Python logging handler that sends messages to Loggly
Home-page: https://github.com/kennedyj/loggly-handler/
Author: Josh Kennedy
Author-email: kennedy.josh@gmail.com
License: MIT
Keywords: loggly logging handler https
Platform: UNKNOWN
Classifier: Development Status :: 4 - Beta
Classifier: Intended Audience :: Developers
